{
  "home": "Головна",
  "library": "Моя бібліотека",
  "reading": "Читання",
  "Log out": "Вийти",
  "filters": "Фільтрувати:",
  "Add to library": "Додати до бібліотеки",
  "Start reading": "Почати читати",
  "Book title:": "Заголовок книги:",
  "Book author:": "Автор книги:",
  "Number of pages:": "К-сть сторінок:",
  "Add book": "Додати книгу",
  "Enter text": "Введіть текст",
  "Start your workout": "Розпочніть читати",
  "Create a personal library": "Створіть власну бібліотеку:",
  "Create your first workout": "Виберіть першу книгу",
  "Add the books you intend to read it": "додайте киги які плануєте прочитати ",
  "Define a goal, choose a period, start training": "визначте цілі, виберіть час, читайте",
  "Books are windows to the world, and reading is a journey into the unknown": "Книги – це вікна у світ, а читання – подорож у невідоме",
  "Recommended books": "Рекомендовані книги",
  "Create your library": "Створюйте власну бібліотеку",
  "All books": "Усі книги",
  "Show all": "Показати всі",
  "Unread": "Непрочитані",
  "Inprogress": "Читаються",
  "Done": "Прочитані",
  "Start page": "Розпочати читати на сторінці:",
  "Stop page": "Закінчити читати на сторінці",
  "Page number": "Номер сторінки:",
  "To start": "Розпочати",
  "To stop": "Завершити",
  "Progress": "Прогрес",
  "Here you will see when and how much you read. To record, click on the red button above": "Тут ви побачите, коли і скільки ви читаєте. Для запису натисніть на кнопку вище",
  "Diary": "Щоденник читання",
  "Statistics": "Статистика",
  "Statistics_message": "Кожна сторінка, кожен розділ – це новий виток знань, новий крок до розуміння. Переписуючи статистику, ми створюємо власну історію читання",
  "pages": "сторінки",
  "days": "день",
  "hours": "годин",
  "minutes": "хвилин",
  "seconds": "секунд",
  "pages per hour": "сторінок за годину",
  "pages read": "сторінок прочитано",
  "Expand your mind, reading": "Розширюйте свій світогляд, читаючи",
  "Name": "Ім'я:",
  "Mail": "Пошта:",
  "Password": "Пароль:",
  "Registrations": "Зареєструватись",
  "Log in": "Увійти",
  "Don't have an account": "Не маєте акаунту ?",
  "Already have an account": "Вже маєте акаунт ?",
  "Books are": "Книги – це",
  "windows": "вікна",
  "book": "книгу",
  "to the world, and reading is a journey into the unknown": "у світ, а читання – подорож у невідоме",
  "exceed_total_pages": "Ви ввели більшу кількість сторінок ніж міститься у книзі"
}
